coordinates/__init__.py
coordinates/client.py
coordinates/converter.py
tests/__init__.py
tests/test_converter.py
tests/test_coordinate_validator.py
coordinates_converter-0.1.0.dist-info/LICENSE
coordinates_converter-0.1.0.dist-info/METADATA
coordinates_converter-0.1.0.dist-info/WHEEL
coordinates_converter-0.1.0.dist-info/entry_points.txt
coordinates_converter-0.1.0.dist-info/top_level.txt
coordinates_converter-0.1.0.dist-info/RECORD
