Metadata-Version: 2.1
Name: coordinates converter
Version: 0.1.0
Summary: L-Est97 to WGS84 coordinates converter with GUI interface
Home-page: https://gitlab.com/eskumu/coordinates-converter/
Author: Kristjan Tärk
Author-email: kristjan.tark@gmail.com
License: UNKNOWN
Platform: UNKNOWN
Classifier: Programming Language :: Python :: 2
Classifier: Programming Language :: Python :: 3
Classifier: License :: OSI Approved :: MIT License
Classifier: Operating System :: OS Independent
